mrbs/__init__.py
mrbs/_version.py
mrbs/clustering.py
mrbs/gradient_ascent.py
mrbs/interpolator.py
mrbs/visualization.py
mrbs-0.1.0.dist-info/METADATA
mrbs-0.1.0.dist-info/WHEEL
mrbs-0.1.0.dist-info/licenses/LICENSE
mrbs-0.1.0.dist-info/RECORD
