Metadata-Version: 2.4
Name: mrbs
Version: 0.1.0
Summary: Model-based Response surface optimization with Bootstrap Sampling - Surface interpolation with XGBoost, gradient ascent path finding, and clustering-based optimal point estimation
Project-URL: Homepage, https://github.com/yutotakagi/MRBS
Project-URL: Repository, https://github.com/yutotakagi/MRBS
Project-URL: Bug Tracker, https://github.com/yutotakagi/MRBS/issues
Author: Yuto Takagi
License: MIT License
License-File: LICENSE
Keywords: clustering,gradient-ascent,machine-learning,optimization,response-surface,surrogate-model,xgboost
Classifier: Development Status :: 3 - Alpha
Classifier: Intended Audience :: Developers
Classifier: Intended Audience :: Science/Research
Classifier: License :: OSI Approved :: MIT License
Classifier: Operating System :: OS Independent
Classifier: Programming Language :: Python :: 3
Classifier: Programming Language :: Python :: 3.9
Classifier: Programming Language :: Python :: 3.10
Classifier: Programming Language :: Python :: 3.11
Classifier: Programming Language :: Python :: 3.12
Classifier: Programming Language :: Python :: 3.13
Classifier: Topic :: Scientific/Engineering
Classifier: Topic :: Scientific/Engineering :: Artificial Intelligence
Requires-Python: >=3.9
Requires-Dist: matplotlib>=3.4
Requires-Dist: numpy>=1.20
Requires-Dist: pandas>=1.3
Requires-Dist: scikit-learn>=1.0
Requires-Dist: xgboost>=1.5
Provides-Extra: dev
Requires-Dist: build>=1.0; extra == 'dev'
Requires-Dist: jupyter>=1.0; extra == 'dev'
Requires-Dist: pytest>=7.0; extra == 'dev'
Requires-Dist: ruff>=0.1.0; extra == 'dev'
Requires-Dist: twine>=4.0; extra == 'dev'
